performance_data_collection/BaseCollect.py
performance_data_collection/MacCollect.py
performance_data_collection/WindowsCollect.py
performance_data_collection/__init__.py
performance_data_collection-1.0.2.dist-info/LICENSE
performance_data_collection-1.0.2.dist-info/METADATA
performance_data_collection-1.0.2.dist-info/WHEEL
performance_data_collection-1.0.2.dist-info/top_level.txt
performance_data_collection-1.0.2.dist-info/RECORD
