Metadata-Version: 2.1
Name: performance-data-collection
Version: 1.0.2
Summary: Collect performance data for PC applications
Home-page: https://gitee.com/chen-xiaokai/windows-performance-collection.git
Author: ['chengxaiokai', 'zhoujunjie']
Author-email: 747469442@qq.com
License: Windows MacOS
Platform: all
Classifier: Intended Audience :: Developers
Classifier: Operating System :: OS Independent
Classifier: Natural Language :: Chinese (Simplified)
Classifier: Programming Language :: Python :: 3.5
Classifier: Programming Language :: Python :: 3.6
Classifier: Programming Language :: Python :: 3.7
Classifier: Programming Language :: Python :: 3.8
Classifier: Topic :: Software Development :: Libraries
Requires-Dist: pyecharts
Requires-Dist: psutil
Requires-Dist: pandas
Requires-Dist: xlrd
Requires-Dist: xlwt
Requires-Dist: openpyxl
